allspice/__init__.py
allspice/allspice.py
allspice/apiobject.py
allspice/baseapiobject.py
allspice/exceptions.py
allspice/ratelimiter.py
allspice/utils/__init__.py
allspice/utils/bom_generation.py
allspice/utils/core.py
allspice/utils/list_components.py
allspice/utils/netlist_generation.py
allspice/utils/retry_generated.py
py_allspice-3.12.0.dist-info/licenses/LICENSE
py_allspice-3.12.0.dist-info/METADATA
py_allspice-3.12.0.dist-info/WHEEL
py_allspice-3.12.0.dist-info/top_level.txt
py_allspice-3.12.0.dist-info/RECORD
