Metadata-Version: 2.4
Name: py-allspice
Version: 3.12.0
Summary: A python wrapper for the AllSpice Hub API
Author-email: "AllSpice, Inc." <maintainers@allspice.io>
License: MIT
Project-URL: Homepage, https://github.com/AllSpiceIO/py-allspice
Keywords: AllSpice,AllSpice Hub,api,wrapper
Requires-Python: >=3.10
License-File: LICENSE
Requires-Dist: requests~=2.32
Requires-Dist: frozendict~=2.4
Provides-Extra: test
Requires-Dist: coverage~=7.10; extra == "test"
Requires-Dist: diff_cover~=9.7; extra == "test"
Requires-Dist: libcst~=1.8.5; extra == "test"
Requires-Dist: MonkeyType~=23.3; extra == "test"
Requires-Dist: pdoc~=15.0; extra == "test"
Requires-Dist: pyright~=1.1; extra == "test"
Requires-Dist: pytest-recording~=0.13; extra == "test"
Requires-Dist: pytest~=8.4; extra == "test"
Requires-Dist: ruff==0.13.2; extra == "test"
Requires-Dist: syrupy~=4.9; extra == "test"
Requires-Dist: types-requests~=2.32; extra == "test"
Requires-Dist: typing_extensions~=4.14; python_version < "3.11" and extra == "test"
Dynamic: license-file
